openacquisition/__init__.py
openacquisition/acquisition_method.py
openacquisition/isolation_windows/isolation_model.py
openacquisition/isolation_windows/isolation_shape.py
openacquisition/isotopes/isotope_spline_db.py
openacquisition/isotopes/isotope_spline_xml_parser.py
openacquisition/mathematics/CubicSpline.py
openacquisition/openacquisition.py
openacquisition-0.1.0.dist-info/LICENSE
openacquisition-0.1.0.dist-info/WHEEL
openacquisition-0.1.0.dist-info/METADATA
openacquisition-0.1.0.dist-info/RECORD
