Metadata-Version: 2.1
Name: openacquisition
Version: 0.1.0
Summary: A package for creating data acquisition methods for mass spectrometers
License: None
Author: Dennis Goldfarb
Requires-Python: >=3.9,<4.0
Classifier: License :: Other/Proprietary License
Classifier: Programming Language :: Python :: 3
Classifier: Programming Language :: Python :: 3.10
Classifier: Programming Language :: Python :: 3.9
Requires-Dist: lazy (>=1.4,<2.0)
Requires-Dist: mistune (>=2.0.4,<3.0.0)
Requires-Dist: pyopenms (>=2.7.0,<3.0.0)
